gql_optimizer/__init__.py
gql_optimizer/cache.py
gql_optimizer/core.py
gql_optimizer/dataloader.py
gql_optimizer/exceptions.py
gql_optimizer/extractors.py
gql_optimizer/utils.py
gql_optimizer-1.0.1.dist-info/METADATA
gql_optimizer-1.0.1.dist-info/WHEEL
gql_optimizer-1.0.1.dist-info/licenses/LICENSE
gql_optimizer-1.0.1.dist-info/RECORD
