Metadata-Version: 2.4
Name: gql-optimizer
Version: 1.0.1
Summary: GraphQL Query Optimizer for SQLAlchemy - Optimize your GraphQL queries with field selection, caching, and DataLoader support
Project-URL: Homepage, https://github.com/Duhan07/graphql-query-optimizer
Project-URL: Documentation, https://github.com/Duhan07/graphql-query-optimizer#readme
Project-URL: Repository, https://github.com/Duhan07/graphql-query-optimizer.git
Project-URL: Issues, https://github.com/Duhan07/graphql-query-optimizer/issues
Project-URL: Changelog, https://github.com/Duhan07/graphql-query-optimizer/blob/main/CHANGELOG.md
Author-email: Duhan Günsel <gnsl.duhan.07@gmail.com>
Maintainer-email: Duhan Günsel <gnsl.duhan.07@gmail.com>
License: MIT
License-File: LICENSE
Keywords: ariadne,cache,dataloader,graphene,graphql,n+1,optimization,performance,query,sqlalchemy,strawberry
Classifier: Development Status :: 4 - Beta
Classifier: Framework :: AsyncIO
Classifier: Intended Audience :: Developers
Classifier: License :: OSI Approved :: MIT License
Classifier: Operating System :: OS Independent
Classifier: Programming Language :: Python :: 3
Classifier: Programming Language :: Python :: 3.9
Classifier: Programming Language :: Python :: 3.10
Classifier: Programming Language :: Python :: 3.11
Classifier: Programming Language :: Python :: 3.12
Classifier: Programming Language :: Python :: 3.13
Classifier: Topic :: Database
Classifier: Topic :: Internet :: WWW/HTTP
Classifier: Topic :: Software Development :: Libraries :: Python Modules
Classifier: Typing :: Typed
Requires-Python: >=3.9
Requires-Dist: sqlalchemy>=2.0.0
Provides-Extra: all
Requires-Dist: aiosqlite>=0.19.0; extra == 'all'
Requires-Dist: ariadne>=0.20.0; extra == 'all'
Requires-Dist: graphene>=3.0.0; extra == 'all'
Requires-Dist: greenlet>=3.0.0; extra == 'all'
Requires-Dist: strawberry-graphql>=0.200.0; extra == 'all'
Provides-Extra: ariadne
Requires-Dist: ariadne>=0.20.0; extra == 'ariadne'
Provides-Extra: async
Requires-Dist: aiosqlite>=0.19.0; extra == 'async'
Requires-Dist: greenlet>=3.0.0; extra == 'async'
Provides-Extra: dev
Requires-Dist: black>=23.0.0; extra == 'dev'
Requires-Dist: build>=1.0.0; extra == 'dev'
Requires-Dist: isort>=5.12.0; extra == 'dev'
Requires-Dist: mypy>=1.0.0; extra == 'dev'
Requires-Dist: pytest-asyncio>=0.21.0; extra == 'dev'
Requires-Dist: pytest-cov>=4.0.0; extra == 'dev'
Requires-Dist: pytest>=7.0.0; extra == 'dev'
Requires-Dist: ruff>=0.1.0; extra == 'dev'
Requires-Dist: twine>=5.0.0; extra == 'dev'
Provides-Extra: docs
Requires-Dist: mkdocs-material>=9.0.0; extra == 'docs'
Requires-Dist: mkdocs>=1.5.0; extra == 'docs'
Requires-Dist: mkdocstrings[python]>=0.24.0; extra == 'docs'
Provides-Extra: graphene
Requires-Dist: graphene>=3.0.0; extra == 'graphene'
Provides-Extra: strawberry
Requires-Dist: strawberry-graphql>=0.200.0; extra == 'strawberry'
